equiflow/__init__.py
equiflow/equiflow.py
equiflow-0.1.9.dist-info/licenses/LICENSE
equiflow-0.1.9.dist-info/METADATA
equiflow-0.1.9.dist-info/WHEEL
equiflow-0.1.9.dist-info/top_level.txt
equiflow-0.1.9.dist-info/RECORD
