Metadata-Version: 2.4
Name: equiflow
Version: 0.1.9
Summary: A package to generate equity-focused cohort selection flow diagrams
Author-email: João Matos <jcmatos@mit.edu>, Jacob Ellen <jgellen4@gmail.com>, Pedro Moreira <pedromoreirah3@gmail.com>
Maintainer-email: João Matos <jcmatos@mit.edu>, Jacob Ellen <jgellen4@gmail.com>, Pedro Moreira <pedromoreirah3@gmail.com>
License: MIT License
Keywords: EquiFlow,flow diagram,cohort,clinical research,machine learning,equity,statistics
Classifier: Development Status :: 3 - Alpha
Classifier: Intended Audience :: Science/Research
Classifier: Intended Audience :: Healthcare Industry
Classifier: License :: OSI Approved :: MIT License
Classifier: Operating System :: OS Independent
Classifier: Programming Language :: Python :: 3
Classifier: Programming Language :: Python :: 3.9
Classifier: Programming Language :: Python :: 3.10
Classifier: Programming Language :: Python :: 3.11
Classifier: Programming Language :: Python :: 3.12
Classifier: Topic :: Scientific/Engineering :: Medical Science Apps.
Classifier: Topic :: Scientific/Engineering :: Visualization
Requires-Python: >=3.9
License-File: LICENSE
Requires-Dist: graphviz
Requires-Dist: matplotlib
Requires-Dist: numpy
Requires-Dist: pandas
Requires-Dist: scipy
Provides-Extra: dev
Requires-Dist: pytest>=7.0; extra == "dev"
Requires-Dist: pytest-cov>=4.0; extra == "dev"
Requires-Dist: ruff>=0.1.0; extra == "dev"
Requires-Dist: build; extra == "dev"
Requires-Dist: twine; extra == "dev"
Provides-Extra: docs
Requires-Dist: sphinx>=7.0; extra == "docs"
Requires-Dist: sphinx-autoapi>=3.0; extra == "docs"
Requires-Dist: furo>=2024.0; extra == "docs"
Provides-Extra: full
Requires-Dist: pygraphviz; extra == "full"
Dynamic: license-file
